santodigital_request_full/__init__.py
santodigital_request_full/conftest.py
santodigital_request_full/validator/UrlValidator.py
santodigital_request_full/validator/__init__.py
santodigital_request_full-1.0.9.dist-info/LICENSE
santodigital_request_full-1.0.9.dist-info/METADATA
santodigital_request_full-1.0.9.dist-info/WHEEL
santodigital_request_full-1.0.9.dist-info/top_level.txt
santodigital_request_full-1.0.9.dist-info/RECORD
