Metadata-Version: 2.1
Name: santodigital-request-full
Version: 1.0.9
Summary: Http request library for paginated response api
Home-page: https://bitbucket.org/santodigital/santodigital-request-full
Author: Rodrigo Gonçalves
Author-email: rodrigo@santodigital.com.br
License: UNKNOWN
Platform: UNKNOWN
Classifier: Programming Language :: Python :: 3
Classifier: License :: OSI Approved :: MIT License
Classifier: Operating System :: OS Independent
Requires-Python: >=3.6
